image_filter_library/__init__.py
image_filter_library/filters.py
image_filter_library-1.0.8.dist-info/METADATA
image_filter_library-1.0.8.dist-info/WHEEL
image_filter_library-1.0.8.dist-info/top_level.txt
image_filter_library-1.0.8.dist-info/RECORD
